autodepgraph/__init__.py
autodepgraph/graph.py
autodepgraph/version.py
autodepgraph/visualization.py
autodepgraph/node_functions/__init__.py
autodepgraph/node_functions/calibration_functions.py
autodepgraph/node_functions/check_functions.py
autodepgraph-0.3.5.dist-info/LICENSE
autodepgraph-0.3.5.dist-info/METADATA
autodepgraph-0.3.5.dist-info/WHEEL
autodepgraph-0.3.5.dist-info/top_level.txt
autodepgraph-0.3.5.dist-info/RECORD
